sqpy/__init__.py
sqpy/dialog_window.py
sqpy/popup_print.py
sqpy/scancel_dialog.py
sqpy/sqpy.py
tests/__init__.py
tests/test_dialog_window.py
tests/test_main.py
tests/test_popup_print.py
tests/test_scancel_dialog.py
tests/test_slurm_viewer.py
sqpy-0.0.3.dist-info/LICENSE
sqpy-0.0.3.dist-info/METADATA
sqpy-0.0.3.dist-info/WHEEL
sqpy-0.0.3.dist-info/entry_points.txt
sqpy-0.0.3.dist-info/top_level.txt
sqpy-0.0.3.dist-info/RECORD
