Metadata-Version: 2.1
Name: sqpy
Version: 0.0.3
Summary: A Python package for interactive slurm squeue
Author-email: Mateusz Zelent <mateusz.zelent@amu.edu.pl>, Mathieu Moalic <matmoa@amu.edu.pl>
Requires-Python: >=3.8
License-File: LICENSE
Provides-Extra: dev
Requires-Dist: pip-tools ; extra == 'dev'
Requires-Dist: pre-commit ; extra == 'dev'
Requires-Dist: pytest ; extra == 'dev'
Requires-Dist: pytest-cov ; extra == 'dev'
Requires-Dist: pytest-mock ; extra == 'dev'
